po.py
po-0.1.0.dist-info/LICENSE
po-0.1.0.dist-info/METADATA
po-0.1.0.dist-info/WHEEL
po-0.1.0.dist-info/top_level.txt
po-0.1.0.dist-info/RECORD
